odoo8_addon_website_anchor_smooth_scroll-8.0.1.0.0.99.dev10-py2.7-nspkg.pth
odoo8_addon_website_anchor_smooth_scroll-8.0.1.0.0.99.dev10.dist-info/DESCRIPTION.rst
odoo8_addon_website_anchor_smooth_scroll-8.0.1.0.0.99.dev10.dist-info/METADATA
odoo8_addon_website_anchor_smooth_scroll-8.0.1.0.0.99.dev10.dist-info/RECORD
odoo8_addon_website_anchor_smooth_scroll-8.0.1.0.0.99.dev10.dist-info/WHEEL
odoo8_addon_website_anchor_smooth_scroll-8.0.1.0.0.99.dev10.dist-info/metadata.json
odoo8_addon_website_anchor_smooth_scroll-8.0.1.0.0.99.dev10.dist-info/namespace_packages.txt
odoo8_addon_website_anchor_smooth_scroll-8.0.1.0.0.99.dev10.dist-info/top_level.txt
odoo_addons/website_anchor_smooth_scroll/README.rst
odoo_addons/website_anchor_smooth_scroll/__init__.py
odoo_addons/website_anchor_smooth_scroll/__openerp__.py
odoo_addons/website_anchor_smooth_scroll/demo/pages.xml
odoo_addons/website_anchor_smooth_scroll/i18n/bg.po
odoo_addons/website_anchor_smooth_scroll/i18n/de.po
odoo_addons/website_anchor_smooth_scroll/i18n/es.po
odoo_addons/website_anchor_smooth_scroll/i18n/fr.po
odoo_addons/website_anchor_smooth_scroll/i18n/it.po
odoo_addons/website_anchor_smooth_scroll/i18n/pt_BR.po
odoo_addons/website_anchor_smooth_scroll/i18n/sl.po
odoo_addons/website_anchor_smooth_scroll/i18n/website_anchor_smooth_scroll.pot
odoo_addons/website_anchor_smooth_scroll/static/description/icon.png
odoo_addons/website_anchor_smooth_scroll/static/src/js/website_anchor_smooth_scroll.js
odoo_addons/website_anchor_smooth_scroll/views/assets.xml
